{"fileType":"ARC-Interactive, history file, version 0.1.0","startTime":"2024-03-07T18:39:19Z","user":"anonymous","dataset":"1D-ARC","task":"1d_recolor_cmp_46","summary":{"history count":9,"reveal count":0,"start over count":0,"test solved count":1,"test unsolved count":0,"show overview count":2},"history":[{"id":0,"wait":0,"message":"welcome to overview"},{"id":1,"wait":6601,"message":"hide overview show editor","context":{"action":"hide overview show editor","imageHandle":"test 0 output","image":[[0,7,7,7,7,7,7,0,0,7,7,0,0,7,7,7,7,7,7,0,7,7,7,7,7,7,0,7,7]]}},{"id":2,"wait":1047,"message":"change tool to fill","context":{"action":"pick tool","toolId":"fill","imageHandle":"test 0 output"}},{"id":3,"wait":1370,"message":"pick color 9","context":{"action":"pick color","sameColor":false,"imageHandle":"test 0 output","color":9}},{"id":4,"wait":2687,"message":"flood fill, x: 4 y: 0 color: 9","context":{"action":"flood fill","sameImage":false,"imageHandle":"test 0 output","x":4,"y":0,"color":9,"image":[[0,9,9,9,9,9,9,0,0,7,7,0,0,7,7,7,7,7,7,0,7,7,7,7,7,7,0,7,7]]}},{"id":5,"wait":1308,"message":"flood fill, x: 15 y: 0 color: 9","context":{"action":"flood fill","sameImage":false,"imageHandle":"test 0 output","x":15,"y":0,"color":9,"image":[[0,9,9,9,9,9,9,0,0,7,7,0,0,9,9,9,9,9,9,0,7,7,7,7,7,7,0,7,7]]}},{"id":6,"wait":815,"message":"flood fill, x: 21 y: 0 color: 9","context":{"action":"flood fill","sameImage":false,"imageHandle":"test 0 output","x":21,"y":0,"color":9,"image":[[0,9,9,9,9,9,9,0,0,7,7,0,0,9,9,9,9,9,9,0,9,9,9,9,9,9,0,7,7]]}},{"id":7,"wait":1411,"message":"submit, correct","context":{"action":"submit","imageHandle":"test 0 output","correct":true,"submitCorrectCount":1,"submitIncorrectCount":0,"startOverCount":0,"showOverviewCount":1,"image":[[0,9,9,9,9,9,9,0,0,7,7,0,0,9,9,9,9,9,9,0,9,9,9,9,9,9,0,7,7]]}},{"id":8,"wait":1434,"message":"hide editor show overview","context":{"action":"hide editor show overview","imageHandle":"test 0 output"}}]}