{"fileType":"ARC-Interactive, history file, version 0.1.0","startTime":"2025-10-16T00:16:22Z","user":"anonymous","dataset":"ARC","task":"b1948b0a","summary":{"history count":25,"reveal count":1,"start over count":0,"test solved count":1,"test unsolved count":0,"show overview count":2},"history":[{"id":0,"wait":0,"message":"all train pairs fit in overview area","context":{"action":"pagination-disabled"}},{"id":1,"wait":2,"message":"welcome to overview"},{"id":2,"wait":7454,"message":"reveal begin"},{"id":3,"wait":142,"message":"reveal end"},{"id":4,"wait":8358,"message":"hide overview show editor","context":{"action":"hide overview show editor","imageHandle":"test 0 output","image":[[6,7,7,6],[6,7,6,7],[7,7,7,6],[7,6,7,6]]}},{"id":5,"wait":2924,"message":"pick color 7","context":{"action":"pick color","sameColor":false,"imageHandle":"test 0 output","color":7}},{"id":6,"wait":1298,"message":"draw, x: 3 y: 2 color: 7","context":{"action":"draw","imageHandle":"test 0 output","sameImage":false,"x":3,"y":2,"color":7,"image":[[6,7,7,6],[6,7,6,7],[7,7,7,7],[7,6,7,6]]}},{"id":7,"wait":999,"message":"draw, x: 3 y: 3 color: 7","context":{"action":"draw","imageHandle":"test 0 output","sameImage":false,"x":3,"y":3,"color":7,"image":[[6,7,7,6],[6,7,6,7],[7,7,7,7],[7,6,7,7]]}},{"id":8,"wait":1359,"message":"draw, x: 2 y: 1 color: 7","context":{"action":"draw","imageHandle":"test 0 output","sameImage":false,"x":2,"y":1,"color":7,"image":[[6,7,7,6],[6,7,7,7],[7,7,7,7],[7,6,7,7]]}},{"id":9,"wait":1047,"message":"draw, x: 2 y: 1 color: 7","context":{"action":"draw","imageHandle":"test 0 output","sameImage":true,"x":2,"y":1,"color":7,"image":[[6,7,7,6],[6,7,7,7],[7,7,7,7],[7,6,7,7]]}},{"id":10,"wait":2291,"message":"pick color 6","context":{"action":"pick color","sameColor":false,"imageHandle":"test 0 output","color":6}},{"id":11,"wait":1663,"message":"draw, x: 3 y: 3 color: 6","context":{"action":"draw","imageHandle":"test 0 output","sameImage":false,"x":3,"y":3,"color":6,"image":[[6,7,7,6],[6,7,7,7],[7,7,7,7],[7,6,7,6]]}},{"id":12,"wait":1212,"message":"draw, x: 3 y: 2 color: 6","context":{"action":"draw","imageHandle":"test 0 output","sameImage":false,"x":3,"y":2,"color":6,"image":[[6,7,7,6],[6,7,7,7],[7,7,7,6],[7,6,7,6]]}},{"id":13,"wait":1195,"message":"draw, x: 2 y: 1 color: 6","context":{"action":"draw","imageHandle":"test 0 output","sameImage":false,"x":2,"y":1,"color":6,"image":[[6,7,7,6],[6,7,6,7],[7,7,7,6],[7,6,7,6]]}},{"id":14,"wait":5293,"message":"hide editor show overview","context":{"action":"hide editor show overview","imageHandle":"test 0 output"}},{"id":15,"wait":8072,"message":"hide overview show editor","context":{"action":"hide overview show editor","imageHandle":"test 0 output","image":[[6,7,7,6],[6,7,6,7],[7,7,7,6],[7,6,7,6]]}},{"id":16,"wait":2553,"message":"pick color 2","context":{"action":"pick color","sameColor":false,"imageHandle":"test 0 output","color":2}},{"id":17,"wait":1581,"message":"draw, x: 3 y: 0 color: 2","context":{"action":"draw","imageHandle":"test 0 output","sameImage":false,"x":3,"y":0,"color":2,"image":[[6,7,7,2],[6,7,6,7],[7,7,7,6],[7,6,7,6]]}},{"id":18,"wait":1222,"message":"draw, x: 2 y: 1 color: 2","context":{"action":"draw","imageHandle":"test 0 output","sameImage":false,"x":2,"y":1,"color":2,"image":[[6,7,7,2],[6,7,2,7],[7,7,7,6],[7,6,7,6]]}},{"id":19,"wait":1470,"message":"draw, x: 3 y: 2 color: 2","context":{"action":"draw","imageHandle":"test 0 output","sameImage":false,"x":3,"y":2,"color":2,"image":[[6,7,7,2],[6,7,2,7],[7,7,7,2],[7,6,7,6]]}},{"id":20,"wait":895,"message":"draw, x: 3 y: 3 color: 2","context":{"action":"draw","imageHandle":"test 0 output","sameImage":false,"x":3,"y":3,"color":2,"image":[[6,7,7,2],[6,7,2,7],[7,7,7,2],[7,6,7,2]]}},{"id":21,"wait":1682,"message":"draw, x: 1 y: 3 color: 2","context":{"action":"draw","imageHandle":"test 0 output","sameImage":false,"x":1,"y":3,"color":2,"image":[[6,7,7,2],[6,7,2,7],[7,7,7,2],[7,2,7,2]]}},{"id":22,"wait":1397,"message":"draw, x: 0 y: 1 color: 2","context":{"action":"draw","imageHandle":"test 0 output","sameImage":false,"x":0,"y":1,"color":2,"image":[[6,7,7,2],[2,7,2,7],[7,7,7,2],[7,2,7,2]]}},{"id":23,"wait":1215,"message":"draw, x: 0 y: 0 color: 2","context":{"action":"draw","imageHandle":"test 0 output","sameImage":false,"x":0,"y":0,"color":2,"image":[[2,7,7,2],[2,7,2,7],[7,7,7,2],[7,2,7,2]]}},{"id":24,"wait":2237,"message":"submit, correct","context":{"action":"submit","imageHandle":"test 0 output","correct":true,"submitCorrectCount":1,"submitIncorrectCount":0,"startOverCount":0,"showOverviewCount":2,"image":[[2,7,7,2],[2,7,2,7],[7,7,7,2],[7,2,7,2]]}}]}